{
  "schemaVersion": 1,
  "deployables": [
    {
      "name": "San.Runtime.Headless",
      "projectPath": "src/Sanctuary/San.Runtime.Headless/San.Runtime.Headless/San.Runtime.Headless.csproj",
      "family": "Sanctuary",
      "artifactKind": "dotnet-publish",
      "publishLane": "runtime-host",
      "includedInFirstPublish": true,
      "promotable": true,
      "requiresHitlForPublication": true,
      "requiredTests": [
        "tests/Sanctuary/Oan.Audit.Tests/Oan.Audit.Tests/Oan.Audit.Tests.csproj",
        "tests/Sanctuary/Oan.Runtime.IntegrationTests/Oan.Runtime.IntegrationTests/Oan.Runtime.IntegrationTests.csproj"
      ],
      "requiredAudits": [
        "workspace-path-hygiene",
        "build-audit",
        "subsystem-audit:CradleTek",
        "subsystem-audit:SoulFrame",
        "subsystem-audit:AgentiCore",
        "subsystem-audit:GovernanceConnective",
        "subsystem-audit:SLI"
      ]
    }
  ]
}
